{
  "name": "Кузница Душ",
  "category": "simulation:dungeons",
  "icon": "cataclysm:monstrous_eye",
  "sortnum": 1,
  "pages": [
    {
      "type": "patchouli:text",
      "title": "Кузница Душ",
      "text": "Не самая редкая находка - кузница разбросана по всему Незеру, от багровых лесов до искажённых, и рано или поздно попадётся сама. Koboleton и Kobolediator копошатся у горнов, маленькие и злые, будто их когда-то было гораздо больше и они до сих пор работают за весь цех."
    },
    {
      "type": "patchouli:entity",
      "entity": "cataclysm:netherite_monstrosity",
      "scale": 0.5,
      "offset": 1.5,
      "rotate": true,
      "default_rotation": -20,
      "name": "Незеритовое Чудовище"
    },
    {
      "type": "patchouli:text",
      "title": "То, что уже не спит",
      "text": "В отличие от прочих логовищ, будить здесь некого - Незеритовое Чудовище уже на ногах, когда вы заходите, и это худшее знакомство из всех. Держите Netherite Effigy при себе - если чудовище всё-таки уйдёт на покой раньше времени, эффигия поднимет его снова, в меньшем и чуть более честном виде."
    }
  ]
}
